scrummy/__init__.py
scrummy/__version__.py
scrummy/config.py
scrummy/constants.py
scrummy/main.py
scrummy/models.py
scrummy/rollover.py
scrummy/utils.py
scrummy-0.2.0.dist-info/LICENSE
scrummy-0.2.0.dist-info/METADATA
scrummy-0.2.0.dist-info/WHEEL
scrummy-0.2.0.dist-info/entry_points.txt
scrummy-0.2.0.dist-info/top_level.txt
scrummy-0.2.0.dist-info/RECORD
