Metadata-Version: 2.1
Name: scrummy
Version: 0.2.0
Summary: Plaintext Scrum-like Todo and Checklist Management
Home-page: https://github.com/mas-4/scrummy
Author: Michael Sendker
Author-email: m@standingwater.io
License: MIT
Project-URL: Homepage, https://github.com/mas-4/scrummy
Project-URL: Source, https://github.com/mas-4/scrummy
Platform: UNKNOWN
Classifier: License :: OSI Approved :: MIT License
Classifier: Programming Language :: Python :: 3
Classifier: Programming Language :: Python :: 3.10
License-File: LICENSE
Requires-Dist: click
Requires-Dist: python-dateutil
Requires-Dist: xdg
